minpiler/__init__.py
minpiler/__main__.py
minpiler/cmdline.py
minpiler/emu.py
minpiler/mast.py
minpiler/mind.py
minpiler/mparse.py
minpiler/optimizer.py
minpiler/test_utils.py
minpiler/typeshed.py
minpiler/utils.py
minpiler-0.3.2.dist-info/entry_points.txt
minpiler-0.3.2.dist-info/LICENSE
minpiler-0.3.2.dist-info/WHEEL
minpiler-0.3.2.dist-info/METADATA
minpiler-0.3.2.dist-info/RECORD
