Metadata-Version: 2.1
Name: minpiler
Version: 0.3.2
Summary: Compile python code to Mindustry microprocessor instructions
Home-page: https://github.com/neumond/minpiler
License: UNKNOWN
Keywords: mindustry,mlog,mlogic,compiler,processor
Author: Vitalik Verhovodov
Author-email: knifeslaughter@gmail.com
Requires-Python: >=3.6
Classifier: Development Status :: 4 - Beta
Classifier: License :: OSI Approved :: MIT License
Classifier: Intended Audience :: Developers
Classifier: Intended Audience :: Education
Classifier: Programming Language :: Python :: 3.6
Classifier: Programming Language :: Python :: 3.7
Classifier: Programming Language :: Python :: 3.8
Classifier: Programming Language :: Python :: 3.9
Classifier: Topic :: Games/Entertainment
Classifier: Topic :: Software Development :: Compilers
Classifier: Topic :: Utilities
Requires-Dist: dataclasses; python_version <= '3.6'
